fabric/__init__.py
fabric/tools/__init__.py
fabric/tools/lakehouse.py
fabric/tools/utils.py
fabric/yamls/lakehouse.yaml
tests/__init__.py
tests/test_lakehouse.py
pffabric-0.0.5.dist-info/METADATA
pffabric-0.0.5.dist-info/WHEEL
pffabric-0.0.5.dist-info/entry_points.txt
pffabric-0.0.5.dist-info/top_level.txt
pffabric-0.0.5.dist-info/RECORD
