Metadata-Version: 2.1
Name: pffabric
Version: 0.0.5
Summary: This package contains promptflow tools for working with Microsoft Fabric Lakehouse.
